<?xml version="1.0" encoding="utf-8" ?>
<dwsync>
<file name="251D35B1-BF5C-4F15-B1C9-F137C256D49A.jpg" server="ftp.brianschooler.com" local="132163916642969386" remote="132179236200000000" Dst="1" />
<file name="30ECE9B0-C647-4A2B-9328-A00002DB3FFB.jpg" server="ftp.brianschooler.com" local="132163916641185389" remote="132179236200000000" Dst="1" />
<file name="37B767A5-DEAD-41C8-A228-51ECF6EFBC32.jpg" server="ftp.brianschooler.com" local="132163916640582849" remote="132179236200000000" Dst="1" />
<file name="3CF19B97-0742-450D-A1C4-65EA6C86017E.jpg" server="ftp.brianschooler.com" local="132163916642351666" remote="132179236200000000" Dst="1" />
<file name="7972701C-36D5-47C9-AB4E-EFFC5215B3AB.jpg" server="ftp.brianschooler.com" local="132163916645042139" remote="132179236200000000" Dst="1" />
<file name="568C5ABE-07F3-4FB8-A7DC-E0702F31B9B0.jpg" server="ftp.brianschooler.com" local="132163916639930639" remote="132179236200000000" Dst="1" />
<file name="A1D24097-D54D-4DEF-A9B6-CF2143A1B222.jpg" server="ftp.brianschooler.com" local="132163916651338635" remote="132179236200000000" Dst="1" />
<file name="30ECE9B0-C647-4A2B-9328-A00002DB3FFB.jpg" server="vcsar1.org" local="132163916641185389" remote="132229366200000000" Dst="1" />
<file name="251D35B1-BF5C-4F15-B1C9-F137C256D49A.jpg" server="vcsar1.org" local="132163916642969386" remote="132229366200000000" Dst="1" />
<file name="37B767A5-DEAD-41C8-A228-51ECF6EFBC32.jpg" server="vcsar1.org" local="132163916640582849" remote="132229366200000000" Dst="1" />
<file name="3CF19B97-0742-450D-A1C4-65EA6C86017E.jpg" server="vcsar1.org" local="132163916642351666" remote="132229366200000000" Dst="1" />
<file name="7972701C-36D5-47C9-AB4E-EFFC5215B3AB.jpg" server="vcsar1.org" local="132163916645042139" remote="132229366200000000" Dst="1" />
<file name="568C5ABE-07F3-4FB8-A7DC-E0702F31B9B0.jpg" server="vcsar1.org" local="132163916639930639" remote="132229366200000000" Dst="1" />
<file name="A1D24097-D54D-4DEF-A9B6-CF2143A1B222.jpg" server="vcsar1.org" local="132163916651338635" remote="132229366200000000" Dst="1" />
</dwsync>